{"stone":[125,125,125],"stone 2":[159,115,98],"stone 1":[153,114,99],"stone 3":[180,180,183],"stone 4":[183,183,186],"stone 6":[133,133,135],"dirt":[134,96,67],"cobblestone":[123,123,123],"stone 5":[131,131,131],"planks":[157,128,79],"planks 1":[104,78,47],"planks 2":[196,179,123],"planks 3":[154,110,77],"planks 4":[169,92,51],"planks 5":[61,40,18],"bedrock":[84,84,84],"gold_ore":[143,140,125],"iron_ore":[136,130,127],"coal_ore":[115,115,115],"log":[102,81,50],"log 0":[155,125,77],"log 1":[105,81,48],"wood 4":[105,99,89],"wood 3":[87,68,27],"sponge":[195,196,85],"lapis_ore":[102,112,135],"sandstone":[217,210,157],"sandstone 1":[216,208,155],"sandstone 2":[220,212,162],"noteblock":[101,68,51],"wool 1":[241,118,20],"wool":[234,236,237],"wool 2":[190,69,180],"wool 3":[58,175,217],"wool 5":[112,185,26],"wool 4":[249,198,40],"wool 6":[238,141,172],"wool 7":[63,68,72],"wool 8":[142,142,135],"wool 9":[21,138,145],"wool 11":[53,57,157],"wool 10":[122,42,173],"wool 12":[114,72,41],"wool 13":[85,110,28],"wool 14":[161,39,35],"wool 15":[21,21,26],"iron_block":[219,219,219],"brick_block":[147,100,87],"tnt":[170,93,71],"bookshelf":[108,88,58],"mossy_cobblestone":[104,121,104],"gold_block":[249,236,79],"obsidian":[20,18,30],"diamond_ore":[129,140,143],"diamond_block":[98,219,214],"crafting_table":[119,96,60],"redstone_ore":[133,107,107],"snow":[240,251,251],"clay":[159,164,177],"soul_sand":[85,64,52],"netherrack":[111,54,53],"stonebrick 3":[119,119,119],"brown_mushroom_block":[142,107,83],"red_mushroom_block":[183,38,36],"melon_block":[141,146,36],"nether_brick":[45,23,27],"end_stone":[221,224,165],"redstone_lamp":[70,43,27],"emerald_ore":[110,129,116],"emerald_block":[81,217,117],"redstone_block":[171,28,9],"quartz_ore":[125,85,80],"quartz_block":[236,233,226],"quartz_block 1":[232,228,220],"stained_hardened_clay":[205,173,156],"quartz_block 2":[232,228,220],"purpur_block 2":[170,126,170],"stained_hardened_clay 1":[162,84,38],"stained_hardened_clay 2":[150,88,109],"stained_hardened_clay 3":[113,109,138],"stained_hardened_clay 4":[186,133,35],"stained_hardened_clay 5":[104,118,53],"stained_hardened_clay 6":[162,78,79],"stained_hardened_clay 8":[135,107,98],"stained_hardened_clay 7":[58,42,36],"stained_hardened_clay 9":[87,91,91],"stained_hardened_clay 10":[118,70,86],"stained_hardened_clay 11":[74,60,91],"stained_hardened_clay 12":[77,51,36],"stained_hardened_clay 13":[76,83,42],"stained_hardened_clay 14":[143,61,47],"stained_hardened_clay 15":[37,23,16],"prismarine":[107,170,151],"prismarine 1":[100,160,143],"prismarine 2":[60,88,75],"hay_block":[158,117,18],"hardened_clay":[151,93,67],"coal_block":[19,19,19],"packed_ice":[165,195,245],"red_sandstone":[166,85,30],"red_sandstone 1":[162,83,28],"red_sandstone 2":[168,86,31],"purpur_block":[166,122,166],"end_bricks":[226,231,171],"nether_wart_block":[117,103,null],"magma":[135,65,25],"bone_block":[225,221,201],"concrete 2":[169,48,159],"concrete 1":[224,97,1],"concrete":[207,213,214],"concrete 3":[36,137,199],"concrete 4":[241,175,21],"concrete 5":[94,169,25],"concrete 6":[214,101,143],"concrete 7":[55,58,62],"concrete 8":[125,125,115],"concrete 10":[100,32,156],"concrete 9":[21,119,136],"concrete 11":[45,47,143],"concrete 12":[96,60,32],"concrete 13":[73,91,36],"concrete 15":[0,0,0],"concrete 14":[142,33,33],"blue_ice":[116,168,253],"dried_kelp_block":[38,49,30],"stripped_oak_log":[164,134,81],"stripped_spruce_log":[113,89,52],"stripped_birch_log":[185,161,104],"stripped_jungle_log":[171,134,85],"stripped_acacia_log":[167,92,59],"stripped_dark_oak_log":[87,69,46],"pumpkin":[195,114,24],"smooth_stone":[158,158,158]}